cb_imaginAIry-0.1.6.data/scripts/cb-aimg
cb_imaginAIry-0.1.6.data/scripts/cb-imagine
imaginairy/__init__.py
imaginairy/animations.py
imaginairy/api.py
imaginairy/colorize.py
imaginairy/config.py
imaginairy/debug_info.py
imaginairy/feather_tile.py
imaginairy/img_utils.py
imaginairy/log_utils.py
imaginairy/lr_scheduler.py
imaginairy/model_manager.py
imaginairy/outpaint.py
imaginairy/paths.py
imaginairy/prompt_schedules.py
imaginairy/roi_utils.py
imaginairy/safety.py
imaginairy/schema.py
imaginairy/surprise_me.py
imaginairy/train.py
imaginairy/utils.py
imaginairy/version.py
imaginairy/cli/__init__.py
imaginairy/cli/colorize.py
imaginairy/cli/describe.py
imaginairy/cli/edit.py
imaginairy/cli/edit_demo.py
imaginairy/cli/imagine.py
imaginairy/cli/main.py
imaginairy/cli/shared.py
imaginairy/cli/train.py
imaginairy/cli/upscale.py
imaginairy/configs/control-net-v15.yaml
imaginairy/configs/instruct-pix2pix.yaml
imaginairy/configs/stable-diffusion-v1-inpaint.yaml
imaginairy/configs/stable-diffusion-v1.yaml
imaginairy/configs/stable-diffusion-v2-inference-v.yaml
imaginairy/configs/stable-diffusion-v2-inference.yaml
imaginairy/configs/stable-diffusion-v2-inpainting-inference.yaml
imaginairy/configs/stable-diffusion-v2-midas-inference.yaml
imaginairy/configs/stable-diffusion-x4-upscaling.yaml
imaginairy/data/DejaVuSans.ttf
imaginairy/enhancers/__init__.py
imaginairy/enhancers/blur_detect.py
imaginairy/enhancers/bool_masker.py
imaginairy/enhancers/clip_masking.py
imaginairy/enhancers/describe_image_blip.py
imaginairy/enhancers/describe_image_clip.py
imaginairy/enhancers/face_restoration_codeformer.py
imaginairy/enhancers/facecrop.py
imaginairy/enhancers/prompt_expansion.py
imaginairy/enhancers/upscale_realesrgan.py
imaginairy/enhancers/upscale_riverwing.py
imaginairy/enhancers/phraselists/__init__.py
imaginairy/enhancers/phraselists/color.txt
imaginairy/enhancers/phraselists/spaceship.txt
imaginairy/img_processors/__init__.py
imaginairy/img_processors/control_modes.py
cb_imaginAIry-0.1.6.dist-info/LICENSE
cb_imaginAIry-0.1.6.dist-info/METADATA
cb_imaginAIry-0.1.6.dist-info/WHEEL
cb_imaginAIry-0.1.6.dist-info/top_level.txt
cb_imaginAIry-0.1.6.dist-info/RECORD
