Metadata-Version: 2.1
Name: cb-imaginAIry
Version: 0.1.6
Summary: AI imagined images. Pythonic generation of stable diffusion images.
Author: Code Burrito
License-File: LICENSE
Requires-Dist: click
Requires-Dist: click-help-colors
Requires-Dist: click-shell
Requires-Dist: protobuf (!=3.19.5,!=3.20.2)
Requires-Dist: facexlib
Requires-Dist: ftfy
Requires-Dist: torch (>=1.13.1)
Requires-Dist: numpy
Requires-Dist: tqdm
Requires-Dist: diffusers
Requires-Dist: imageio (>=2.9.0)
Requires-Dist: Pillow (>=8.0.0)
Requires-Dist: psutil
Requires-Dist: pytorch-lightning (>=1.4.2)
Requires-Dist: omegaconf (>=2.1.1)
Requires-Dist: open-clip-torch
Requires-Dist: opencv-python
Requires-Dist: requests
Requires-Dist: einops (>=0.3.0)
Requires-Dist: safetensors
Requires-Dist: timm (>=0.4.12)
Requires-Dist: torchdiffeq
Requires-Dist: transformers (>=4.19.2)
Requires-Dist: triton (>=2.0.0a2)
Requires-Dist: torchmetrics (>=0.6.0)
Requires-Dist: torchvision (>=0.13.1)
Requires-Dist: kornia (>=0.6)
Requires-Dist: xformers (>=0.0.16) ; sys_platform != "darwin"
